ticketreminder/__init__.py
ticketreminder/api.py
ticketreminder/db_default.py
ticketreminder/htdocs/css/ticketreminder.css
ticketreminder/htdocs/js/ticketreminder.js
ticketreminder/templates/ticket_reminder_add.html
ticketreminder/templates/ticket_reminder_delete.html
TicketReminderPlugin-0.2.1.dist-info/METADATA
TicketReminderPlugin-0.2.1.dist-info/WHEEL
TicketReminderPlugin-0.2.1.dist-info/entry_points.txt
TicketReminderPlugin-0.2.1.dist-info/top_level.txt
TicketReminderPlugin-0.2.1.dist-info/RECORD
