Metadata-Version: 2.1
Name: TicketReminderPlugin
Version: 0.2.1
Summary: Allows to configure reminders for tickets in Trac.
Home-page: https://github.com/trac-hacks/trac-ticketreminder
Author: Mitar
Author-email: mitar.trac@tnode.com
License: AGPLv3
Keywords: trac plugin
Platform: UNKNOWN
